Workbook

Sheet Resumen KPI
A1: CSPX — iShares Core S&P 500 UCITS ETF (Acc)
A2: Informe histórico 2021-2026 (detalle 2022-2026) y pronóstico a 6 meses — ISIN IE00B5BMR087
A3: Fecha de análisis: 2026-08-10 | Fecha de corte de datos: 2026-08-04 a 2026-08-10 | Analista/agente: bolsa-europa (Asesor Financiero)
A4: AVISO: documento educativo de análisis personal, no es asesoría financiera profesional. Los escenarios de pronóstico son opinión del analista, no un hecho verificado.
A6: Indicadores clave (KPI)
A7: KPI | B7: Valor | C7: Unidad | D7: Fuente / fecha
A8: Precio actual (línea LSE, CSPX.L) | B8: 835.72 | C8: USD | D8: Yahoo Finance / stockanalysis.com, 2026-08-07
A9: Rango 52 semanas — mínimo | B9: 665 | C9: USD | D9: Yahoo Finance / stockanalysis.com, 2026-08-10
A10: Rango 52 semanas — máximo | B10: 839 | C10: USD | D10: Yahoo Finance / stockanalysis.com, 2026-08-10
A11: Rentabilidad YTD 2026 (aprox.) | B11: 0.1362 | C11: % | D11: stockanalysis.com / investing.com, 2026-08-04
A12: TER (comisión total anual) | B12: 0.0007 | C12: % | D12: Morningstar / Yahoo Finance, 2026-07-29
A13: P/E forward S&P 500 (referencia índice) | B13: 20.2 | C13: x | D13: GuruFocus / FactSet, 2026-08-07
A14: P/E trailing S&P 500 (referencia índice) | B14: 26.4 | C14: x | D14: GuruFocus / FactSet, 2026-08-07
A15: Tasa Fed (Federal Funds Rate, techo) | B15: 0.0375 | C15: % | D15: Reserva Federal, 2026-07-29 (mantenida, voto 9-3)
A16: Tasa BCE (facilidad de depósito) | B16: 0.0225 | C16: % | D16: BCE, 2026-07-23 (mercado descuenta subida 10-sep-2026)
A17: Tasa Banco de Inglaterra (Bank Rate) | B17: 0.0375 | C17: % | D17: Prensa financiera UK, 2026-07-30
A18: EUR/USD | B18: 1.1561 | C18: ratio | D18: BCE eurofxref / agregadores, 2026-08-10
A19: GBP/USD | B19: 1.3486 | C19: ratio | D19: Agregadores de mercado, 2026-08-10
A21: Métricas calculadas (fórmulas sobre la hoja 'Rentabilidad Anual')
A22: Métrica | B22: Valor | C22: Unidad | D22: Nota
A23: Mejor año del periodo (rentabilidad) | B23: =MAX('Rentabilidad Anual'!B5:B10) -> 0.2984 | C23: % | D23: Incluye 2026 YTD (parcial)
A24: Peor año del periodo (rentabilidad) | B24: =MIN('Rentabilidad Anual'!B5:B10) -> -0.1932 | C24: % | D24: Incluye 2026 YTD (parcial)
A25: Rentabilidad media anual (simple, 2021-2025) | B25: =AVERAGE('Rentabilidad Anual'!B5:B9) -> 0.16084 | C25: % | D25: Solo años calendario completos 2021-2025
A26: CAGR 2021-2025 (5 años completos) | B26: =('Historico Indexado'!B10/'Historico Indexado'!B5)^(1/5)-1 -> 0.14417552 | C26: % | D26: Tasa de crecimiento anual compuesta 2021-2025 (5 años completos)
A27: Volatilidad (desv. estándar) rentabilidad anual 2021-2025 | B27: =STDEV('Rentabilidad Anual'!B5:B9) -> 0.20250324 | C27: % | D27: Desv. estándar de rentabilidades anuales 2021-2025 (no es la volatilidad diaria/anualizada oficial del proveedor)
A28: Índice acumulado (base 100 = fin 2020) a la fecha de corte | B28: ='Historico Indexado'!B11 -> 222.80147 | C28: pts | D28: Base 100 = fin de 2020; a fecha de corte 2026-08-10 (parcial)
A30: Leyenda: texto azul = dato de entrada (hardcoded, con fuente citada) · texto negro = fórmula calculada.

Sheet Rentabilidad Anual
A1: Rentabilidad anual de CSPX (total return en USD, dividendos reinvertidos, clase Acc)
A2: 2021 se incluye como año de contexto/arranque de la ventana de 5 años exigida por CLAUDE.md §4.4; el foco solicitado por el usuario son los últimos 4 años (2022-2026).
A4: Año | B4: Rentabilidad anual | C4: ¿Año negativo? | D4: Fuente | E4: Fecha de consulta
A5: 2021 | B5: 0.2984 | C5: =IF(B5<0,"Sí","No") -> No | D5: Yahoo Finance / Morningstar (reutilizado de ficha 2026-07-24) | E5: 2026-07-24
A6: 2022 | B6: -0.1932 | C6: =IF(B6<0,"Sí","No") -> Sí | D6: Yahoo Finance / Morningstar (reutilizado de ficha 2026-07-24) | E6: 2026-07-24
A7: 2023 | B7: 0.2612 | C7: =IF(B7<0,"Sí","No") -> No | D7: Yahoo Finance / Morningstar (reutilizado de ficha 2026-07-24) | E7: 2026-07-24
A8: 2024 | B8: 0.2573 | C8: =IF(B8<0,"Sí","No") -> No | D8: Yahoo Finance / Morningstar (reutilizado de ficha 2026-07-24) | E8: 2026-07-24
A9: 2025 | B9: 0.1805 | C9: =IF(B9<0,"Sí","No") -> No | D9: Yahoo Finance / Morningstar (reutilizado de ficha 2026-07-24) | E9: 2026-07-24
A10: 2026 (YTD, parcial) | B10: 0.1362 | C10: =IF(B10<0,"Sí","No") -> No | D10: stockanalysis.com / investing.com (agregador) | E10: 2026-08-04
A12: Nota: 2026 es un año parcial (year-to-date), no un cierre de año.

Sheet Historico Indexado
A1: Rentabilidad acumulada indexada de CSPX (base 100 = cierre de 2020)
A2: Cálculo propio derivado de la tabla de rentabilidades anuales verificadas (hoja 'Rentabilidad Anual'); no es una serie de precios de cierre real del proveedor. El punto de 2026 es un año parcial (YTD).
A4: Fin de periodo | B4: Índice (base 100 = fin 2020) | C4: Nota
A5: 2020 (referencia, fuera de la ventana de 5 años) | B5: 100 | C5: Punto de partida fijado en 100 por convención.
A6: 2021 | B6: =B5*(1+'Rentabilidad Anual'!B5) -> 129.84
A7: 2022 | B7: =B6*(1+'Rentabilidad Anual'!B6) -> 104.75491
A8: 2023 | B8: =B7*(1+'Rentabilidad Anual'!B7) -> 132.1169
A9: 2024 | B9: =B8*(1+'Rentabilidad Anual'!B8) -> 166.11057
A10: 2025 | B10: =B9*(1+'Rentabilidad Anual'!B9) -> 196.09353
A11: 2026 (YTD, parcial) | B11: =B10*(1+'Rentabilidad Anual'!B10) -> 222.80147 | C11: Año parcial (YTD), no cierre de año.
A13: Crecimiento acumulado del periodo (2020 → fecha de corte) | B13: =B11/B5-1 -> 1.2280147

Sheet Escenarios 6M
A1: Pronóstico a 6 meses de CSPX (10-ago-2026 a ~10-feb-2027)
A2: OPINIÓN / PROYECCIÓN EDUCATIVA del analista — no es un hecho verificado ni una recomendación de inversión. Rentabilidad en USD, sin efecto de divisa para el inversor europeo.
A4: Escenario | B4: Rango mínimo | C4: Rango máximo | D4: Supuestos clave (resumen) | E4: Rango (pp)
A5: Alcista | B5: 0.08 | C5: 0.14 | D5: Reapertura del Estrecho de Ormuz normaliza el petróleo; Fed no sube en septiembre; BCE sube sin generar inestabilidad; resultados T3 de las 'Magnificent Seven' sorprenden al alza. | E5: =C5-B5 -> 0.06
A6: Base | B6: 0 | C6: 0.07 | D6: Petróleo estable en 90-100 USD/barril; Fed mantiene tasas en 3.50%-3.75%; BCE ejecuta la subida ya descontada del 10-sep-2026 sin corrección significativa; volatilidad puntual sin escalada mayor. | E6: =C6-B6 -> 0.07
A7: Bajista | B7: -0.14 | C7: -0.03 | D7: Colapsan las negociaciones de Ormuz y se reactiva el conflicto con Irán; Fed y BCE endurecen más de lo esperado; corrección en las 'Magnificent Seven'; agravamiento del frente de Ucrania. | E7: =C7-B7 -> 0.11
A27: Nota metodológica: el gráfico usa una barra base invisible (=mínimo del rango) apilada bajo una barra visible (=máximo-mínimo) para representar el rango de cada escenario en un único eje.

Sheet Fuentes y Notas
A1: Fuentes consultadas y notas de transparencia
A3: Documento fuente completo: bolsas/europa/historia-instrumentos/2026-08-10-cspx-historia-4-anos-pronostico.md
A5: Fuentes principales:
A6: - Banco Central Europeo (BCE) — https://www.ecb.europa.eu, consultado 2026-08-10.
A7: - Reuters (vía Investing.com) — decisión del BCE y expectativa de subida en septiembre de 2026, consultado 2026-08-10.
A8: - Bloomberg — decisión de la Fed del 29 de julio de 2026, consultado 2026-08-10.
A9: - Euronews — decisión del BCE de junio de 2026 y balance del acuerdo 'Turnberry', consultado 2026-08-10.
A10: - Yahoo Finance — cotización de CSPX.L / CSPX.AS / CSSPX.MI / CSP1.L, consultado 2026-08-10.
A11: - Morningstar — ficha de rendimiento y perfil de CSPX, consultado 2026-07-29 (reutilizado).
A12: - Investing.com — cotización histórica de CSPX y de EUR/USD, consultado 2026-08-10.
A13: - CNN Business / CNBC — máximos históricos del S&P 500 en agosto de 2026, consultado 2026-08-10.
A14: - Federal Reserve — calendario oficial de reuniones del FOMC 2026, consultado 2026-08-10.
... A23: Este archivo es un complemento tabular/visual del informe en Markdown; en caso de discrepancia, el Markdown es la fuente autoritativa citada con fuente y fecha por cada dato.
